reactive_deliberative/__init__.py
reactive_deliberative/reactive_deliberative.py
reactive_deliberative/py_rete/__init__.py
reactive_deliberative/py_rete/alpha.py
reactive_deliberative/py_rete/beta.py
reactive_deliberative/py_rete/bind_node.py
reactive_deliberative/py_rete/common.py
reactive_deliberative/py_rete/conditions.py
reactive_deliberative/py_rete/fact.py
reactive_deliberative/py_rete/filter_node.py
reactive_deliberative/py_rete/join_node.py
reactive_deliberative/py_rete/ncc_node.py
reactive_deliberative/py_rete/negative_node.py
reactive_deliberative/py_rete/network.py
reactive_deliberative/py_rete/pnode.py
reactive_deliberative/py_rete/production.py
reactive_deliberative-0.1.3.dist-info/LICENSE
reactive_deliberative-0.1.3.dist-info/METADATA
reactive_deliberative-0.1.3.dist-info/WHEEL
reactive_deliberative-0.1.3.dist-info/top_level.txt
reactive_deliberative-0.1.3.dist-info/RECORD
