Metadata-Version: 2.1
Name: reactive-deliberative
Version: 0.1.3
Summary: Reactive-deliberative architecture framework
Home-page: https://github.com/mivallion/reactive_deliberative
Author: mivallion
Author-email: mivallion@gmail.com
Project-URL: Bug Tracker, https://github.com/mivallion/reactive_deliberative/issues
Classifier: Programming Language :: Python :: 3
Classifier: License :: OSI Approved :: MIT License
Classifier: Operating System :: OS Independent
Requires-Python: >=3.7
License-File: LICENSE
